soxr-0.4.0.dist-info/WHEEL
soxr-0.4.0.dist-info/LICENSE.txt
soxr-0.4.0.dist-info/COPYING.LGPL
soxr-0.4.0.dist-info/top_level.txt
soxr-0.4.0.dist-info/RECORD
soxr-0.4.0.dist-info/METADATA
soxr/_version.py
soxr/csoxr.pxd
soxr/csoxr_version.c
soxr/soxr-config.h
soxr/__init__.pxd
soxr/cysoxr.c
soxr/cysoxr.cpython-312-x86_64-linux-gnu.so
soxr/csoxr_version.h
soxr/cysoxr.pyx
soxr/__init__.py
soxr/_csoxr_version.c
