Metadata-Version: 2.1
Name: soxr
Version: 0.4.0
Summary: High quality, one-dimensional sample-rate conversion library
Home-page: https://github.com/dofuuz/python-soxr
Author: Myungchul Keum
License: LGPLv2.1+
Project-URL: Documentation, https://python-soxr.readthedocs.io
Project-URL: Source, https://github.com/dofuuz/python-soxr
Project-URL: Bug Tracker, https://github.com/dofuuz/python-soxr/issues
Keywords: audio resampling,samplerate conversion,SRC,signal processing,resampler
Classifier: Development Status :: 4 - Beta
Classifier: Intended Audience :: Developers
Classifier: Intended Audience :: Science/Research
Classifier: Intended Audience :: Telecommunications Industry
Classifier: Topic :: Multimedia :: Sound/Audio :: Analysis
Classifier: Topic :: Multimedia :: Sound/Audio :: Conversion
Classifier: Topic :: Scientific/Engineering
Classifier: License :: OSI Approved :: GNU Lesser General Public License v2 or later (LGPLv2+)
Classifier: Programming Language :: C
Classifier: Programming Language :: Cython
Classifier: Programming Language :: Python :: 3
Requires-Python: >=3.9
License-File: LICENSE.txt
License-File: COPYING.LGPL
Requires-Dist: numpy
Provides-Extra: docs
Requires-Dist: sphinx ; extra == 'docs'
Requires-Dist: sphinx-book-theme ; extra == 'docs'
Requires-Dist: myst-parser ; extra == 'docs'
Requires-Dist: linkify-it-py ; extra == 'docs'
Provides-Extra: test
Requires-Dist: pytest ; extra == 'test'
